chiral/__init__.py
chiral/py.typed
chiral-0.1.0.dist-info/METADATA
chiral-0.1.0.dist-info/WHEEL
chiral-0.1.0.dist-info/licenses/LICENSE
chiral-0.1.0.dist-info/RECORD
